navec/__init__.py
navec/meta.py
navec/navec.py
navec/pq.py
navec/record.py
navec/tar.py
navec/tests.py
navec/vocab.py
navec/train/__init__.py
navec/train/glove.py
navec/train/log.py
navec/train/pq.py
navec/train/quantiles.py
navec/train/s3.py
navec/train/tokens.py
navec/train/ctl/__init__.py
navec/train/ctl/__main__.py
navec/train/ctl/cooc.py
navec/train/ctl/corpus.py
navec/train/ctl/emb.py
navec/train/ctl/merge.py
navec/train/ctl/pack.py
navec/train/ctl/pq.py
navec/train/ctl/s3.py
navec/train/ctl/tokenize.py
navec/train/ctl/vocab.py
navec-0.10.0.dist-info/LICENSE
navec-0.10.0.dist-info/METADATA
navec-0.10.0.dist-info/WHEEL
navec-0.10.0.dist-info/entry_points.txt
navec-0.10.0.dist-info/top_level.txt
navec-0.10.0.dist-info/RECORD
