Metadata-Version: 2.1
Name: navec
Version: 0.10.0
Summary: Compact high quality word embeddings for russian language
Home-page: https://github.com/natasha/navec
Author: Alexander Kukushkin
Author-email: alex@alexkuk.ru
License: MIT
Keywords: embeddings,word2vec,glove,nlp,russian,quantization
Platform: UNKNOWN
Classifier: License :: OSI Approved :: MIT License
Classifier: Programming Language :: Python :: 3
Classifier: Topic :: Scientific/Engineering :: Artificial Intelligence
